{
	"configurations" : 
	[
		{
			"directories" : 
			[
				{
					"build" : ".",
					"hasInstallRule" : true,
					"jsonFile" : "directory-.-510ca4faee60de0de724.json",
					"minimumCMakeVersion" : 
					{
						"string" : "3.12"
					},
					"projectIndex" : 0,
					"source" : ".",
					"targetIndexes" : 
					[
						0,
						1,
						2,
						3
					]
				}
			],
			"name" : "",
			"projects" : 
			[
				{
					"directoryIndexes" : 
					[
						0
					],
					"name" : "joystick",
					"targetIndexes" : 
					[
						0,
						1,
						2,
						3
					]
				}
			],
			"targets" : 
			[
				{
					"directoryIndex" : 0,
					"id" : "joystick::@6890427a1f51a3e7e1df",
					"jsonFile" : "target-joystick-8bbcee8988229269792d.json",
					"name" : "joystick",
					"projectIndex" : 0
				},
				{
					"directoryIndex" : 0,
					"id" : "joystick_uninstall::@6890427a1f51a3e7e1df",
					"jsonFile" : "target-joystick_uninstall-97a6639fd016d45e629e.json",
					"name" : "joystick_uninstall",
					"projectIndex" : 0
				},
				{
					"directoryIndex" : 0,
					"id" : "teleop_joy_node::@6890427a1f51a3e7e1df",
					"jsonFile" : "target-teleop_joy_node-7e107cbab41a23b27b5b.json",
					"name" : "teleop_joy_node",
					"projectIndex" : 0
				},
				{
					"directoryIndex" : 0,
					"id" : "uninstall::@6890427a1f51a3e7e1df",
					"jsonFile" : "target-uninstall-291dfca8b2164844611a.json",
					"name" : "uninstall",
					"projectIndex" : 0
				}
			]
		}
	],
	"kind" : "codemodel",
	"paths" : 
	{
		"build" : "/home/tamir/autonomous_robot/build/joystick",
		"source" : "/home/tamir/autonomous_robot/autonomous_robot_control/src/joystick"
	},
	"version" : 
	{
		"major" : 2,
		"minor" : 3
	}
}
